Workbook

Sheet Sheet1
A1: TFS # | B1: Size | C1: FPI Resource | D1: ID | E1: FCE | F1: YKE | G1: AgC | H1: FCW | I1: NW | J1: Originator | K1: FCE Numeric Rating | L1: YKE Numeric Rating | M1: AgC Numeric Rating | N1: FCW Numeric Rating | O1: FCW Numeric Rating | P1: Avg Rating | Q1: Requestor Priority | R1: Description | S1: Notes | T1: Business Need | U1: INC# | V1: Comments | W1: Modified | X1: Interested Associations | Y1: Solution | Z1: Path
A2: 98716 | B2: Large | C2: PS | D2: 24 | E2: Before EmP-web | F2: Before EmP-web | G2: Before EmP-web | H2: After EmP-web | I2: After EmP-web | J2: AgC | K2: =VLOOKUP(E2,RatingLookup!$A$2:$B$7,2,FALSE) -> 3 | L2: =VLOOKUP(F2,RatingLookup!$A$2:$B$7,2,FALSE) -> 3 | M2: =VLOOKUP(G2,RatingLookup!$A$2:$B$7,2,FALSE) -> 3 | N2: =VLOOKUP(H2,RatingLookup!$A$2:$B$7,2,FALSE) -> 2 | O2: =VLOOKUP(I2,RatingLookup!$A$2:$B$7,2,FALSE) -> 2 | P2: =(AVERAGE(K2:O2)) -> 2.6 | Q2: Medium | R2: Cannot release UCC after loan is paid off Description: AgCountry releases the UCC after the loan is paid off using a 1354 tran code. If there are no loans remaining open for the customer, FPI has to delete the UCC via script to remove it from the tracking report. If there are open loans, the user has to “trick” CW by linking the UCC to a different Security Agreement, then open the UCC modal and delete the UCC. | T2: Business need: Staff sometimes get confused about when they can “trick” the system and when they have to request deletion by FPI. Fundamentally, we don’t like creating data/relationships that are inaccurate if we can avoid it. | V2: Same as FCE row 8. (BT) YKE: We have been told to clean these up prior to closing the loan...but this is not feasible. This is impacting operations and should be dealt with sooner rather than later. FCW-We had this issue when we first went live. FPI adjusted our empower sidebar report to allow it to only show Active accounts. If the loan is paid off, the UCC info will not appear on the report. It has been released, just not "deleted" in our system, so a "clean up item" rather than a data integrity item. We are also using CT Liens to file our UCC's so we basically have a backup of all our UCC data through them. NW - The NW UCC tracking is done in relationships plans in EmPOWER. FCE - We think that this is a time waster for FPI staff and a fix would create efficiencies for FPI and ACA staff. | W2: 42508.655 | X2: Farm Credit East; Yankee; Northwest | Y2: ​Always bring back UCC's tied to closed loans and show them as orphaned UCC's. Fix the deletion issue where they get submitted even if not tied to a Sec Agree. Non issue for Empower Web as the UCC Maintenance Utility will always bring them back. | Z2: Workspaces/Shared/WorkPlanOC/Lists/Collateral Web Enhancements
A3: 98716 | B3: Large | C3: PS | D3: 35 | E3: Before EmP-web | F3: Before EmP-web | G3: Before EmP-web | H3: After EmP-web | I3: After EmP-web | J3: FCE | K3: =VLOOKUP(E3,RatingLookup!$A$2:$B$7,2,FALSE) -> 3 | L3: =VLOOKUP(F3,RatingLookup!$A$2:$B$7,2,FALSE) -> 3 | M3: =VLOOKUP(G3,RatingLookup!$A$2:$B$7,2,FALSE) -> 3 | N3: =VLOOKUP(H3,RatingLookup!$A$2:$B$7,2,FALSE) -> 2 | O3: =VLOOKUP(I3,RatingLookup!$A$2:$B$7,2,FALSE) -> 2 | P3: =(AVERAGE(K3:O3)) -> 2.6 | Q3: High | R3: Combined with #24 Currently FCE's process is to close the account with the xx54 tran code then later remove the UCC from the tickler system. Currently in Collateral Web once the loan is closed the UCC disappears (but remains on the UCC reports) and can only be deleted by asking FPI to run a scrip to remove it. | V3: NW - GMM - haven't run across this yet but makes sense. YKE: this is a duplicate of #24 FCW - Same comment as #24 above. FCE - This has to be a very time consuming process for FPI staff to close UCC's when requested by staff. There should be a more efficient way. | W3: 42508.654 | X3: Farm Credit East; Yankee; Northwest | Y3: ​Always bring back UCC's tied to closed loans and show them as orphaned UCC's. Fix the deletion issue where they get submitted even if not tied to a Sec Agree. Non issue for Empower Web as the UCC Maintenance Utility will always bring them back. | Z3: Workspaces/Shared/WorkPlanOC/Lists/Collateral Web Enhancements
A4: 98717 | B4: Config Only | C4: PS | D4: 4 | E4: After EmP-web | F4: Before EmP-web | G4: After EmP-web | H4: After EmP-web | I4: Before EmP-web | J4: NW | K4: =VLOOKUP(E4,RatingLookup!$A$2:$B$7,2,FALSE) -> 2 | L4: =VLOOKUP(F4,RatingLookup!$A$2:$B$7,2,FALSE) -> 3 | M4: =VLOOKUP(G4,RatingLookup!$A$2:$B$7,2,FALSE) -> 2 | N4: =VLOOKUP(H4,RatingLookup!$A$2:$B$7,2,FALSE) -> 2 | O4: =VLOOKUP(I4,RatingLookup!$A$2:$B$7,2,FALSE) -> 3 | P4: =(AVERAGE(K4:O4)) -> 2.4 | Q4: High | R4: Income Capacity of Real Estate Option in Real Property Smart Data Wizard Description: Add an attribute in the Real Property smart data wizard to input Income Capacity of Real Estate information for loans secured by property >$250k. At Northwest FCS, if a loan is >$250k and includes real property collateral, the normalized income capacity must be identified for that piece of real estate. We compare normalized income capacity to the required debt service of the loans secured to the property to determine whether the property itself has adequate income potential to service the debt or whether the borrower would need to rely on other sources for repayment. | T4: Business Need: Procedure is to include Income Capacity of Real Estate information in the Credit Summary; however this does not always happen. Creating this field as a Real Property collateral attribute would enable consistency in completing credit analysis, improved compliance with procedure and ease in finding the information. Note – this field would not be required as it only needs to be completed when the property value is >$250k. | V4: AgC Comments: This was on the original CW requirements list as #41, Build ML DCR calculator. All assocations do a variation of this, but AgCountry agreed to engage our Custom Solutions Group to develop a solution for AgCountry. (BT) NW- The field would be needed when the loan amount is > $250k not the property value. The attribute could read: If loans is great than $250K complete income capacity of real estate comments. YKE: We are doing this now completely outside of any FPI provided system (in Excel). Then post to ECB. Not efficient and not available in anyway for reporting. This is a great suggestion. FCW - We added in a Acres, Income, Debt Service area on all of our RE icons in Web. Not sure this is what is needed but that is how FCW handles accounting for the Income on the property. Staff completes information outside of Collateral Web and inputs into Narrative as well as Web. FCE - We do not handle it this way. | W4: 42508.651 | X4: Yankee; Northwest | Y4: ​This could all be done via Configs. Add a new Question in Check All That apply, and if checked, display a new Other Info Topic Panel to gather this info. Already flows to MR as well. | Z4: Workspaces/Shared/WorkPlanOC/Lists/Collateral Web Enhancements
A5: 98718 | B5: Very Large | C5: PS | D5: 16 | E5: After EmP-web | F5: After EmP-web | G5: Before EmP-web | H5: Before EmP-web | I5: After EmP-web | J5: FCW | K5: =VLOOKUP(E5,RatingLookup!$A$2:$B$7,2,FALSE) -> 2 | L5: =VLOOKUP(F5,RatingLookup!$A$2:$B$7,2,FALSE) -> 2 | M5: =VLOOKUP(G5,RatingLookup!$A$2:$B$7,2,FALSE) -> 3 | N5: =VLOOKUP(H5,RatingLookup!$A$2:$B$7,2,FALSE) -> 3 | O5: =VLOOKUP(I5,RatingLookup!$A$2:$B$7,2,FALSE) -> 2 | P5: =(AVERAGE(K5:O5)) -> 2.4 | R5: History – This would be beneficial for staff to see what was completed in a previous scenario and by who. Currently the only way to do this is, is to go into Empower and try and figure out what was completed in Collateral web via Collateral Details screen. Once EmPower is replaced by EmPower Web there is a concern the forensics of a collateral problem completed by Strategy will be lost. | T5: Business need: We need to have the ability to look back through historical actions to conduct forensics in EmPower Web. Currently this is used for auditing and training purposes. If this is not preserved there will be no "why" and "how" as to what happened on a collateral error. | V5: AgC Comments: We need to have the ability to look back through historical actions to conduct forensics, both in CW and EmP Web. We can't readily validate the data files we send to AgriBank without the history. Would want to know who booked the action, when and what it contained (similar to EmP today) NW - BRIAN: I agree with this being valuable for us from a research / audit trail standpoint, but for me (NW) this is a lower priority than all the others on the FCW list. We have good controls for what exists and falls off for scenarios, and how data really gets committed to the database via the EmPOWER submittal process. I don’t see this as getting worse with the advent of EmPOWER Web as Brittany noted, but I’m could be missing something. YKE: This is a data governance issue, to be dealt with holistically by Empower Web FCW - Needs to be considered along with the development of Empower Web (that the history from the Collateral Web scenarios needs to be archived or at least reviewable -- currently scenario detail goes away when the loan is booked). FCE - We would use the narrative to find out what the collateral was from previous actions. Not sure it is worth developing within CW. | W5: 42508.652 | X5: Farm Credit East; Yankee; Farm Credit West; Northwest | Y5: ​Add New Link in the Scenario Drop Down called "Historic Scenarios". When clicked, open a new Modal that brings back all Historic Scenarios for this Customer and related Customers. Add Buttons to Close window or Open Historic Scenario Read Only. Submit button needs to be clickable but still read only. Non Issue for Empower Web as this is already planned. | Z5: Workspaces/Shared/WorkPlanOC/Lists/Collateral Web Enhancements
A6: 98719 | B6: Large | C6: CW | D6: 21 | E6: After EmP-web | F6: Before EmP-web | G6: Before EmP-web | H6: On Hold | I6: Before EmP-web | J6: AgC | K6: =VLOOKUP(E6,RatingLookup!$A$2:$B$7,2,FALSE) -> 2 | L6: =VLOOKUP(F6,RatingLookup!$A$2:$B$7,2,FALSE) -> 3 | M6: =VLOOKUP(G6,RatingLookup!$A$2:$B$7,2,FALSE) -> 3 | N6: =VLOOKUP(H6,RatingLookup!$A$2:$B$7,2,FALSE) -> 1 | O6: =VLOOKUP(I6,RatingLookup!$A$2:$B$7,2,FALSE) -> 3 | P6: =(AVERAGE(K6:O6)) -> 2.4 | Q6: Medium | R6: Loan group changes not recognized in CW Description: CW does not appear to recognize changes to loan groups after a credit action has been linked to CW. Group errors fire in error, requiring workarounds in EmPOWER to undo the group changes, refresh CW to remove errors & submit changes, then modify the group in EmPOWER. INC0157904 | T6: Business need: Due to the business environment, we’re seeing a lot of restructuring and change in direction as RM’s work through their credit analysis. Group changes are common as guarantees are added, collateral owners changed, etc. This issue results in potential data issues, extra work, staff confusion and delayed loan closing. Any time we modify data to make something “work” we introduce risk that the data will not be corrected. When users receive these errors, they struggle, then contact the AgCountry help desk, and finally may end up with the FPI help desk before successfully booking the loan. | U6: INC0157904 | V6: NW - GMM –I am border line between 1 and 2 for significant or minor positive impact. I haven’t tested this but think that it would be of value to NW provided it is behaving the same way. If we haven’t heard about this issue yet, we probably will in the future. TLD - I haven't heard this. Usually when folks get a hard error about a group change, they start a GM, change the group, and link the open action to the current scenario. The few times I've heard of people doing it, it seems to work fine CMC - Agreed, better to be proactive than reactive here. YKE: We have not encountered this yet BUT are attempting to clean up group names. If changing a Group name caused this, we would want this improved sooner rather than later. If this is due to change in Group Members, then this also needs to be addressed soon. FCW-Have not had issues like this at FCW. SImilar to NW, if an error occurs, users address group issues and seems to work. Not heard issues from our end. FCE - Have not heard of this being an issue but agree it should recognize changes to loan groups. | W6: 42508.654 | X6: Farm Credit East; Yankee; Northwest | Y6: ​Change logic to always refresh from linked loan action for group changes when refreshing scenario or opening scenario. | Z6: Workspaces/Shared/WorkPlanOC/Lists/Collateral Web Enhancements
A7: 98720 | B7: Very Large | C7: CW | D7: 25 | E7: After EmP-web | F7: Before EmP-web | G7: Before EmP-web | H7: After EmP-web | I7: After EmP-web | J7: AgC | K7: =VLOOKUP(E7,RatingLookup!$A$2:$B$7,2,FALSE) -> 2 | L7: =VLOOKUP(F7,RatingLookup!$A$2:$B$7,2,FALSE) -> 3 | M7: =VLOOKUP(G7,RatingLookup!$A$2:$B$7,2,FALSE) -> 3 | N7: =VLOOKUP(H7,RatingLookup!$A$2:$B$7,2,FALSE) -> 2 | O7: =VLOOKUP(I7,RatingLookup!$A$2:$B$7,2,FALSE) -> 2 | P7: =(AVERAGE(K7:O7)) -> 2.4 | Q7: Medium | R7: Partial release functionality does not work for building values Description: Building values cannot be adjusted using partial release functionality. INC0156420 | T7: Business need: We don’t often take buildings, but when we need to release them we can’t use the PR functionality. | U7: INC0156420 | V7: YKE: we have not run into this yet but we would need to be able to take into account buildings being released. FCW-Not an issue at FCW. FCE - Not an issue at FCE | W7: 42508.655 | X7: Yankee; Northwest | Y7: ​Show Building Type, Description and Value as child Grid under each Detail RE record and allow only the entire buiklding to be releases. Also properly recalculate the MV improvements value. We show them the building grid on the partial release panel and let them check the "buildings" that they want to release. Then do a calculation to reduce the MV improvements by that amount. If we are changing this section and pushing to MV improvements should we also add a MV vs. MV improvement fields so they can parcel the amount to release between the two (Noticed by FCE). | Z7: Workspaces/Shared/WorkPlanOC/Lists/Collateral Web Enhancements
A8: 98722 | D8: 41 | E8: After EmP-web | F8: After EmP-web | G8: After EmP-web | H8: After EmP-web | I8: After EmP-web | J8: FCE | K8: =VLOOKUP(E8,RatingLookup!$A$2:$B$7,2,FALSE) -> 2 | L8: =VLOOKUP(F8,RatingLookup!$A$2:$B$7,2,FALSE) -> 2 | M8: =VLOOKUP(G8,RatingLookup!$A$2:$B$7,2,FALSE) -> 2 | N8: =VLOOKUP(H8,RatingLookup!$A$2:$B$7,2,FALSE) -> 2 | O8: =VLOOKUP(I8,RatingLookup!$A$2:$B$7,2,FALSE) -> 2 | P8: =(AVERAGE(K8:O8)) -> 2 | Q8: Medium | R8: This is how I understand the lock in Collateral Web. When entering collateral web it defaults to current production. It is not until you change to a different scenario that the lock message appears (see Ryan’s email below for testing he did). The message fades away. Request is to make the lock work more like Credit Pro…See Kate’s email. Should get the lock message as soon as you enter the customer and have user click to continue. | V8: NW - GMM - Consistency is what is important here in my opinion. I haven't really gotten any complaints about the locking so far. Yankee agrees this would be nice but willing to wait for Empower Web FCW-Not an issue at FCW. FCE - Efficiency and to assist with multiple users working ont he same customer. | W8: 42473.752 | X8: Farm Credit East; Yankee; Northwest | Z8: Workspaces/Shared/WorkPlanOC/Lists/Collateral Web Enhancements
A9: 92357 | B9: Very Large | C9: CW | D9: 40 | E9: Before EmP-web | F9: After EmP-web | G9: Before EmP-web | H9: Withdrawn | I9: After EmP-web | J9: FCE | K9: =VLOOKUP(E9,RatingLookup!$A$2:$B$7,2,FALSE) -> 3 | L9: =VLOOKUP(F9,RatingLookup!$A$2:$B$7,2,FALSE) -> 2 | M9: =VLOOKUP(G9,RatingLookup!$A$2:$B$7,2,FALSE) -> 3 | N9: =VLOOKUP(H9,RatingLookup!$A$2:$B$7,2,FALSE) -> 0 | O9: =VLOOKUP(I9,RatingLookup!$A$2:$B$7,2,FALSE) -> 2 | P9: =(AVERAGE(K9:O9)) -> 2 | Q9: High | R9: Goal is to reduce the number of multiple collateral scenarios. It is probably infrequent that staff would want to create multiple scenarios for the same group of loans. Would like a warning if possible. It is one of the enhancement discussed in the attached email. | S9: If you press the launch button in EmPOWER, this creates a new scenario and links the action (if there is not already a scenario connected to the action). NOTE TO SELF: Can configure the number of scenarios that can be created at one time by ACA. AgCountry likes to keep ST loans separate from LT loans. | V9: AgC Comments: Similar to our #5, provide visibility into which scenario owns which object. This could be a first step. NW - GMM - This was a big issue in the beginning but support and information has helped folks to stop creating as many extra scenarios. I still see these from time to time. TLD - Agree with Gina, however some folks are still getting into Web for the first time so i see it picking up again as we go into the summer. Seems like a nobrainer CMC - I would agree here with both Gina and Tiago. YKE: we don't encounter multiple scenarios often FCW-As mentioned in the AgC request, once our staff learned and did it incorrectly, they didn't do it again. It's a training issue and staff will get used to being aware of scenarios that are open and reviewing the history prior to opening new scenarios. FCE - As we understand it the multiple scenario option was created to allow staff to : "play in the sandbox" and create different collateral scenarios and then select which one they want to use. Unfortunately staff are finding themselves playing in "quicksand" and before they know it they are in too deep and need help getting pulled back out. This has been by far the biggest hurdle for staff. They don't understand the multiple scenarios and end up creating scenarios that can never be released so they end up losing data and having to start all over. What should happen is the system should not allow multiple scenarios for the same scope of loans that share collateral. An error should pop up if staff do try to create multiple scenarios. This will greatly enhance efficiency, training time and staff frustrations with collateral web. | W9: 42508.654 | X9: Farm Credit East; Yankee; Northwest | Y9: ​Once a Scenario has anything being edited in a System scope, then any other Scenarios would lock that system scope out from changes and inform the user as to why it is locked. Would also need to prevent during the opening/linking Commitment Action to Scenario and/or creating Scenario, that if the loan is in a locked system scope then a new scenario wont be created. | Z9: Workspaces/Shared/WorkPlanOC/Lists/Collateral Web Enhancements
A10: 98724 | B10: Medium | C10: PS | D10: 3 | E10: After EmP-web | F10: Withdrawn | G10: On Hold | H10: Before EmP-web | I10: Before EmP-web | J10: NW | K10: =VLOOKUP(E10,RatingLookup!$A$2:$B$7,2,FALSE) -> 2 | L10: =VLOOKUP(F10,RatingLookup!$A$2:$B$7,2,FALSE) -> 0 | M10: =VLOOKUP(G10,RatingLookup!$A$2:$B$7,2,FALSE) -> 1 | N10: =VLOOKUP(H10,RatingLookup!$A$2:$B$7,2,FALSE) -> 3 | O10: =VLOOKUP(I10,RatingLookup!$A$2:$B$7,2,FALSE) -> 3 | P10: =(AVERAGE(K10:O10)) -> 1.8 | Q10: High | R10: ‘Flood Zone’ Field in Real Property Smart Data Wizard Description: Add a Flood Zone field to the Buildings and Improvements panel for Real Property collateral. This field is net-new. | T10: Business Need: Regulatory compliance requires we document and maintain structural flood zone information for the lifetime of applicable loans. The only way users can do this now is by entering the information in the Description field. While this does satisfy the compliance requirement, there is still a high risk of human error and we are unable to use any information in the Description field for reporting purposes. What we are seeing is without a visible field, users are forgetting to input flood zone information. Furthermore, information entered in a description field cannot pull into the Collateral Universe. A Flood Zone field tied to the Collateral Universe will enable our Business Intelligence team to generate reports with flood zone information when regulators require it. This currently would be a manual process. | V10: NW - Agreed need to have this one due to compliance requirements. This is for the FEMA indicator and there is not a place for it currently. YKE: review your configurations as this field is available at both the Summary and Detail level for Yankee when you check the All that Apply box. The Buildings panel has the Flood Haz fields. Unless what you are looking for is the actual Flood Zone indicator itself (value from a map) FCW - We are reviewing this internally to determine how this needs to be captured. We don't use the Buildings panel, but (per Yankee) should look into this, as it would be nice for reporting. FCE - We don't see a need for this at FCE, we simply track whether or not insurance is required at this point. We use the "in flood zone" indicator on the building tab. | W10: 42508.651 | X10: Farm Credit West; Northwest | Y10: ​Configuration only change, add a new Other Information Topic Panel. This flows all the way to MR already so no additional work. | Z10: Workspaces/Shared/WorkPlanOC/Lists/Collateral Web Enhancements
A11: 98725 | D11: 10 | E11: After EmP-web | F11: After EmP-web | G11: After EmP-web | H11: On Hold | I11: After EmP-web | J11: NW | K11: =VLOOKUP(E11,RatingLookup!$A$2:$B$7,2,FALSE) -> 2 | L11: =VLOOKUP(F11,RatingLookup!$A$2:$B$7,2,FALSE) -> 2 | M11: =VLOOKUP(G11,RatingLookup!$A$2:$B$7,2,FALSE) -> 2 | N11: =VLOOKUP(H11,RatingLookup!$A$2:$B$7,2,FALSE) -> 1 | O11: =VLOOKUP(I11,RatingLookup!$A$2:$B$7,2,FALSE) -> 2 | P11: =(AVERAGE(K11:O11)) -> 1.8 | R11: Real Property collateral type: the overall # of acres field should sum the # of acres field for each detail. Currently this does not happen and a soft error fires when validated to input the # of acres. | V11: YKE: nice to have if this rolled up for stress testing and reporting total acres. FCW - Nice to have. Not a priority. FCE - Agree this should happen. Not a high priority as FCE usually does not use multiple rows for RE Collateral | W11: 42473.744 | X11: Yankee; Northwest | Z11: Workspaces/Shared/WorkPlanOC/Lists/Collateral Web Enhancements
A12: 98726 | D12: 11 | E12: After EmP-web | F12: After EmP-web | G12: After EmP-web | H12: On Hold | I12: After EmP-web | J12: NW | K12: =VLOOKUP(E12,RatingLookup!$A$2:$B$7,2,FALSE) -> 2 | L12: =VLOOKUP(F12,RatingLookup!$A$2:$B$7,2,FALSE) -> 2 | M12: =VLOOKUP(G12,RatingLookup!$A$2:$B$7,2,FALSE) -> 2 | N12: =VLOOKUP(H12,RatingLookup!$A$2:$B$7,2,FALSE) -> 1 | O12: =VLOOKUP(I12,RatingLookup!$A$2:$B$7,2,FALSE) -> 2 | P12: =(AVERAGE(K12:O12)) -> 1.8 | R12: When completing a Partial Release – if someone submits the action multiple times to EmPOWER, Collateral Web is recording the history for each submit. The collateral web should only keep the last submitted information based on when action is booked. | T12: YKE: we think the issue here is legitimate as the business need is to "propose" a release and produce documents, then book when approved. It would be nice to have a way to stage or propose a PR before an actual approval. FCW - Need a demo to fully understand request. FCE - Sounds logical. FCE does not use P/R function much so not a high priority | W12: 42473.744 | X12: Yankee; Northwest | Z12: Workspaces/Shared/WorkPlanOC/Lists/Collateral Web Enhancements
A13: 98727 | D13: 7 | E13: After EmP-web | F13: After EmP-web | G13: After EmP-web | H13: Withdrawn | I13: After EmP-web | J13: NW | K13: =VLOOKUP(E13,RatingLookup!$A$2:$B$7,2,FALSE) -> 2 | L13: =VLOOKUP(F13,RatingLookup!$A$2:$B$7,2,FALSE) -> 2 | M13: =VLOOKUP(G13,RatingLookup!$A$2:$B$7,2,FALSE) -> 2 | N13: =VLOOKUP(H13,RatingLookup!$A$2:$B$7,2,FALSE) -> 0 | O13: =VLOOKUP(I13,RatingLookup!$A$2:$B$7,2,FALSE) -> 2 | P13: =(AVERAGE(K13:O13)) -> 1.6 | Q13: Minor | R13: UI: Color scheme in Collateral Web Color scheme is difficult/impossible to see the red lines that need to be cleaned up for color blind people | T13: This came up to be in a training in Seattle Fisheries; however, the credit officer who made this suggestion is no longer at Northwest. I haven’t heard it elsewhere so it’s probably a low priority. | V13: NW -Not priority to me. Depending on what you do it could change it for someone else. FCW-Not a Priority at FCW. Before we went live at FCW in August of 2014, a usability group analyzed Collateral web and actually enhanced many icons, colors etc. to make it easier on the eyes. You have the ability to make the background blank, which helps view the red/dotted lines. Use of filters also helps. FCE - Not a priority for us. | W13: 42473.743 | X13: Northwest | Z13: Workspaces/Shared/WorkPlanOC/Lists/Collateral Web Enhancements
A14: 98728 | D14: 13 | E14: After EmP-web | F14: Withdrawn | G14: After EmP-web | H14: After EmP-web | I14: After EmP-web | J14: NW | K14: =VLOOKUP(E14,RatingLookup!$A$2:$B$7,2,FALSE) -> 2 | L14: =VLOOKUP(F14,RatingLookup!$A$2:$B$7,2,FALSE) -> 0 | M14: =VLOOKUP(G14,RatingLookup!$A$2:$B$7,2,FALSE) -> 2 | N14: =VLOOKUP(H14,RatingLookup!$A$2:$B$7,2,FALSE) -> 2 | O14: =VLOOKUP(I14,RatingLookup!$A$2:$B$7,2,FALSE) -> 2 | P14: =(AVERAGE(K14:O14)) -> 1.6 | R14: When you import Inventory/Growing Crops (not sure of other COA) it imports the “Commodity” field into the description line in collateral web instead of the “Description” field from Credit Pro. It does import the “description” field into the comments field in web but when looking in web or the COLA you could have multiple detailed items named “wheat”. Should be winter wheat and spring wheat. | V14: FCW-Has not been brought up as an issue with our staff. Low priority for us. FCE - Not a high priority but would have to see to better understand | W14: 42473.745 | X14: Northwest | Z14: Workspaces/Shared/WorkPlanOC/Lists/Collateral Web Enhancements
A15: 98729 | D15: 26 | E15: After EmP-web | F15: Withdrawn | G15: After EmP-web | H15: After EmP-web | I15: After EmP-web | J15: AgC | K15: =VLOOKUP(E15,RatingLookup!$A$2:$B$7,2,FALSE) -> 2 | L15: =VLOOKUP(F15,RatingLookup!$A$2:$B$7,2,FALSE) -> 0 | M15: =VLOOKUP(G15,RatingLookup!$A$2:$B$7,2,FALSE) -> 2 | N15: =VLOOKUP(H15,RatingLookup!$A$2:$B$7,2,FALSE) -> 2 | O15: =VLOOKUP(I15,RatingLookup!$A$2:$B$7,2,FALSE) -> 2 | P15: =(AVERAGE(K15:O15)) -> 1.6 | Q15: Low | R15: Not sure how to use partial release functionality to release an RE object Description: We create one collateral object per RE appraisal, and some mortgages are secured by multiple objects. We aren’t sure how to use the partial release functionality to track the release of an entire object, but we do need to keep track of releases so staff can easily tell that the original mortgage covers more real estate than we currently have. | T15: Business need: Doesn't allow the flexibility we need to match the business environment. | V15: NW - GMM – This seems like something NW would want as well. I know that people are doing this so visibility into what is released when an entire piece of collateral is let go would be great. Nice to have. FCW- Nice to have. Not a priority. FCE - We don't use PR Functionality much | W15: 42473.753 | X15: Northwest | Z15: Workspaces/Shared/WorkPlanOC/Lists/Collateral Web Enhancements
A16: 98731 | D16: 28 | E16: After EmP-web | F16: After EmP-web | G16: After EmP-web | H16: Withdrawn | I16: After EmP-web | J16: AgC | K16: =VLOOKUP(E16,RatingLookup!$A$2:$B$7,2,FALSE) -> 2 | L16: =VLOOKUP(F16,RatingLookup!$A$2:$B$7,2,FALSE) -> 2 | M16: =VLOOKUP(G16,RatingLookup!$A$2:$B$7,2,FALSE) -> 2 | N16: =VLOOKUP(H16,RatingLookup!$A$2:$B$7,2,FALSE) -> 0 | O16: =VLOOKUP(I16,RatingLookup!$A$2:$B$7,2,FALSE) -> 2 | P16: =(AVERAGE(K16:O16)) -> 1.6 | Q16: Low | R16: CW requires separate credit action for Autobook functionality Description: AgCountry originally designated our Branch Maintenance credit action to be available for autobook. We did not want to add another action and create another “decision” about which type of action to select in CW; the user would check “autobook” if applicable. However, adding the autobook designation to Branch Maintenance seemed to affect the behavior of the branch maintenance even if we didn’t check autobook, so we had to turn the functionality off. | T16: Business need: This was a really neat feature, but we couldn’t support adding a separate credit action to be able to use the feature. Our objective was to simplify the business process, not add another decision point, so we turned it off. | V16: YKE: Autobook is a great concept but we are not able to use it. Would be nice to re-think how this could be enabled, especially for loans where all that has occurred is amortization (same collateral value, just a reduce P balance) FCW - Not an issue. FCE - We don't use autobook | W16: 42473.753 | X16: Yankee; Northwest | Z16: Workspaces/Shared/WorkPlanOC/Lists/Collateral Web Enhancements
A17: 98732 | D17: 14 | E17: After EmP-web | F17: Withdrawn | G17: On Hold | H17: After EmP-web | I17: On Hold | J17: FCW | K17: =VLOOKUP(E17,RatingLookup!$A$2:$B$7,2,FALSE) -> 2 | L17: =VLOOKUP(F17,RatingLookup!$A$2:$B$7,2,FALSE) -> 0 | M17: =VLOOKUP(G17,RatingLookup!$A$2:$B$7,2,FALSE) -> 1 | N17: =VLOOKUP(H17,RatingLookup!$A$2:$B$7,2,FALSE) -> 2 | O17: =VLOOKUP(I17,RatingLookup!$A$2:$B$7,2,FALSE) -> 1 | P17: =(AVERAGE(K17:O17)) -> 1.2 | R17: Autobook – The checkbox is being missed by staff and actions end up not being booked in LOS. Need a way to signify that it will not be booked without the box checked (or possibly come up with a new action name that is only used for AutoBook actions that will be autobooked without a box checked). At the least, need a warning the Autobook box was not checked. | T17: Business need: The ability to Autobook feature added in for collateral remaining was an enhancement to the original collateral app. It helped to bring back the sync feature. We have quite a few open actions that result in intervening actions since these remain open. We have tried to train to check the box, yet it is forgotten by the user. There is a need for a warning that the Autobook box was not checked | V17: AgC Comments: We catch these with an open action report; we have a regular monitoring process for unbooked actions. NW - BRIAN: This is also a concern (actions unintentionally not being booked when the box wasn’t checked). Heidi and the Field Ops team have started sending out after-the-fact reporting on this to make sure actions aren’t sitting out there when they shouldn’t be (just looking for Collateral Update – Autobooks). They run one the LOS Activity reports in the EmPOWER sidebar to do this. I think the warning message is a good idea, but we definitely don’t want to force it. The reason? There are frequently situations where they don’t want an action to automatically go to “ready for booking” so other related loans can all be booked on the same day. In that situation, they just choose the same process definition but don’t check the box. I would spend too many chips on this one, but the benefit is there. Honestly, everything is a much lower priority than the LGD items we have discussed (and were on your list Lorrie). Insight and clarity in CW on when the LGD is being re-calc’d and when it isn’t should easily be our #1 priority from a data governance / control / audit standpoint for our field users. I view the rest as ‘gravy’, including this one. YKE: we are not using Autobook often as we still need to print something to justify why Collateral changed for the loan NOT being serviced. If this was solely due to amortization this would be acceptable. FCW- Warning message or business rule is all we need. Just a friendly reminder that if you want it to book and use this functionality, check the box. FCE - Have not used autobook and is not a high priority | W17: 42479.382 | X17: Farm Credit West | Z17: Workspaces/Shared/WorkPlanOC/Lists/Collateral Web Enhancements
A18: 98733 | D18: 36 | E18: After EmP-web | F18: Withdrawn | G18: After EmP-web | H18: Withdrawn | I18: After EmP-web | J18: FCE | K18: =VLOOKUP(E18,RatingLookup!$A$2:$B$7,2,FALSE) -> 2 | L18: =VLOOKUP(F18,RatingLookup!$A$2:$B$7,2,FALSE) -> 0 | M18: =VLOOKUP(G18,RatingLookup!$A$2:$B$7,2,FALSE) -> 2 | N18: =VLOOKUP(H18,RatingLookup!$A$2:$B$7,2,FALSE) -> 0 | O18: =VLOOKUP(I18,RatingLookup!$A$2:$B$7,2,FALSE) -> 2 | P18: =(AVERAGE(K18:O18)) -> 1.2 | Q18: Medium | R18: collateral ratios are not using peak amount like they should which forces users to override all-in loan amount. This shouldn't be necessary. | V18: NW -Would be useful on loan balances when MOB/controlled above is used. YKE: we don't use Peak FCW-Not an issue at FCW. Our staff uses the override feature on the majority of our PCA loans to reflect peak. FCE - To calculate correct LGD without the need to over ride loan amount | W18: 42473.751 | X18: Farm Credit East; Northwest | Z18: Workspaces/Shared/WorkPlanOC/Lists/Collateral Web Enhancements
A19: 98734 | D19: 6 | E19: After EmP-web | F19: Withdrawn | H19: On Hold | I19: After EmP-web | J19: NW | K19: =VLOOKUP(E19,RatingLookup!$A$2:$B$7,2,FALSE) -> 2 | L19: =VLOOKUP(F19,RatingLookup!$A$2:$B$7,2,FALSE) -> 0 | M19: =0 -> 0 | N19: =VLOOKUP(H19,RatingLookup!$A$2:$B$7,2,FALSE) -> 1 | O19: =VLOOKUP(I19,RatingLookup!$A$2:$B$7,2,FALSE) -> 2 | P19: =(AVERAGE(K19:O19)) -> 1 | Q19: High | R19: Add another new column in the Quick Loan Analysis grid, called “Account Title” Simply display the Account Title that is also on each green loan icon. This makes it much easier to identify which loan is which for the user. I would place it to the right of either the existing Loan # or the Type, but we can let NW decide if this gets approved. Alternatively, if there is a configurable option to change the hyperlink blue Loan # to instead be the Account Title (not adding a new column), this would work as well. | T19: Business Need. Analysis efficiency and loan identification. The loan # is not meaningful to most users from an identification perspective, but the account title is very meaningful since July 2013. | V19: NW - GMM - ANYWHERE that the Loan number shows it would be great if we could add account title. Agreed. Most staff know the loans by account title not account number. FCW-We dealt with this in the first build of CW. There is just not enough room on the Loan icons for this information. We included it on the back side of the Loan icons, that is association configurable. Its a nice to have to have it added to the Quick Loan Analysis area, but it is listed in the Calc Overview modal. Would like to see how much work it entails... | W19: 42473.354 | X19: Northwest | Z19: Workspaces/Shared/WorkPlanOC/Lists/Collateral Web Enhancements
A20: 98735 | D20: 5 | E20: After EmP-web | F20: Withdrawn | G20: Withdrawn | H20: Withdrawn | I20: After EmP-web | J20: NW | K20: =VLOOKUP(E20,RatingLookup!$A$2:$B$7,2,FALSE) -> 2 | L20: =VLOOKUP(F20,RatingLookup!$A$2:$B$7,2,FALSE) -> 0 | M20: =VLOOKUP(G20,RatingLookup!$A$2:$B$7,2,FALSE) -> 0 | N20: =VLOOKUP(H20,RatingLookup!$A$2:$B$7,2,FALSE) -> 0 | O20: =VLOOKUP(I20,RatingLookup!$A$2:$B$7,2,FALSE) -> 2 | P20: =(AVERAGE(K20:O20)) -> 0.8 | Q20: High | R20: Add a new column to the Quick Loan Analysis grid on the Collateral View Display the current LGD in a new column, to the far right, next to the L/NRV% (which is called LTV in EMPOWER LOS) that determines LGD. Make sure the LGD is displaying the “live” data from any (re)calculation that just happened in EmPOWER LOS. | T20: a. Business Need: All of the Collateral Analysis process with field staff is ultimately to determine the LGD on the loan. Displaying the end result of all the ratio and security analysis will put a “bow” on the Collateral package, and give insight into when the LGD may be different than what they had intended. This will increase efficiency and decrease the frequency of previously-submitted scenarios having to be touched in CW. It should also decrease a few of the Transfer Scenario instances and Technical Amendments. b. Need to Discuss: Would NW also want to add the LGD to the Calc Overview section as shown below, especially since a screen shot is taken of this and pasted into the current Credit Summary? | V20: NW - Agreed. FCW-Our staff are aware of the thresholds for LGD so this is not an issue. Even if you have submitted a scenario and notice the LGD is not what you expected, you are able to adjust your submitted scenarios and re submit data back to Empower. I do not see how this would help with transfer scenario instances? FCE - Not sure this is needed . FCE calculates LGD on CU screen in LOS, can be overridden. Might be a consideration with Empower Web if this becomes the place LGD is calculated. | W20: 42479.381 | X20: Northwest | Z20: Workspaces/Shared/WorkPlanOC/Lists/Collateral Web Enhancements
A21: 98736 | D21: 30 | E21: After EmP-web | F21: Withdrawn | G21: Withdrawn | H21: Withdrawn | I21: Withdrawn | J21: FCE | K21: =VLOOKUP(E21,RatingLookup!$A$2:$B$7,2,FALSE) -> 2 | L21: =VLOOKUP(F21,RatingLookup!$A$2:$B$7,2,FALSE) -> 0 | M21: =VLOOKUP(G21,RatingLookup!$A$2:$B$7,2,FALSE) -> 0 | N21: =VLOOKUP(H21,RatingLookup!$A$2:$B$7,2,FALSE) -> 0 | O21: =VLOOKUP(I21,RatingLookup!$A$2:$B$7,2,FALSE) -> 0 | P21: =(AVERAGE(K21:O21)) -> 0.4 | Q21: Medium | R21: Example of issue: If $5,000,000 of the Face Amount was on property with an NRV of $1,000,000 and $645,000 of face amount was on property valued at $10,0000,000 the most that could be collected is $1,645,000 which is less than the combined loan amount thus it would be limited. Additional details in email saved under "Calculations" for EmPower Web...SLR email. | V21: NW - GMM - would like more info on this one. Not sure if it is something NW would want or not. TLD - Seconded CMC - Agree | W21: 42473.75 | X21: Farm Credit East | Z21: Workspaces/Shared/WorkPlanOC/Lists/Collateral Web Enhancements
A22: 98737 | D22: 9 | E22: Withdrawn | F22: Withdrawn | G22: Withdrawn | H22: Withdrawn | I22: After EmP-web | J22: NW | K22: =VLOOKUP(E22,RatingLookup!$A$2:$B$7,2,FALSE) -> 0 | L22: =VLOOKUP(F22,RatingLookup!$A$2:$B$7,2,FALSE) -> 0 | M22: =VLOOKUP(G22,RatingLookup!$A$2:$B$7,2,FALSE) -> 0 | N22: =VLOOKUP(H22,RatingLookup!$A$2:$B$7,2,FALSE) -> 0 | O22: =VLOOKUP(I22,RatingLookup!$A$2:$B$7,2,FALSE) -> 2 | P22: =(AVERAGE(K22:O22)) -> 0.4 | Q22: High | R22: UCC Error Message The error message that says a UCC is required fires for Chattels but sometimes UCC’s are also required on RE when there are fixtures. It would be great if the error was enhanced so that if fixtures like Irrigation Equipment or Permanent Plantings were included in the RE collateral then the error would fire for those as well. Today it never fires for RE even though a UCC might actually be required. | T22: This would help ensure that UCC's are properly recorded when necessary | V22: NW - Please discuss with Rachel Swanson and Michelle Ferrara. I know I asked about this during testing and after roll-out. They had reasonings on why the business rules are set the way they are. YKE: can this be a Config change? FCW-Not a priority at FCW. Different business rules than we use.... FCE - Not a priority | W22: 42473.744 | X22: Northwest | Z22: Workspaces/Shared/WorkPlanOC/Lists/Collateral Web Enhancements

Sheet RatingLookup
A1: Label | B1: Rating
B2: 0
A3: Withdrawn | B3: 0
A4: On Hold | B4: 1
A5: After EmP-web | B5: 2
A6: Before EmP-web | B6: 3
